polarweb/__init__.py
polarweb/main.py
polar_web-0.0.2.dist-info/LICENSE
polar_web-0.0.2.dist-info/METADATA
polar_web-0.0.2.dist-info/WHEEL
polar_web-0.0.2.dist-info/top_level.txt
polar_web-0.0.2.dist-info/RECORD
